[
    {
        "id": 0, 
        "boxes": {
            "0": [
                {
                    "width": 1017,
                    "height": 801,
                    "top": 276,
                    "left": 30
                }
            ]
        }
    },
    {
        "id": 1,
        "boxes": {
            "0": [
                {
                    "width": 188,
                    "height": 152,
                    "top": 96,
                    "left": 23
                }
            ],
            "1": [
                {
                    "width": 193,
                    "height": 156,
                    "top": 92,
                    "left": 254
                }
            ],
            "2": [
                {
                    "width": 184,
                    "height": 157,
                    "top": 91,
                    "left": 479
                }
            ],
            "3": [
                {
                    "width": 190,
                    "height": 153,
                    "top": 308,
                    "left": 20
                }
            ],
            "4": [
                {
                    "width": 196,
                    "height": 153,
                    "top" :308,
                    "left": 246
                }
            ],
            "5": [
                {
                    "width": 192,
                    "height": 153,
                    "top": 308,
                    "left": 471
                }
            ]
        }
    },
    {
        "id": 2,
        "boxes": {
            "0": [
                {
                    "width": 455,
                    "height": 351,
                    "top": 365,
                    "left": 0
                }
            ]
        }
    },
    {
        "id": 3,
        "boxes": {
            "0": [
                {
                    "width": 468,
                    "height": 484,
                    "top": 135,
                    "left": 31
                }
            ],
            "1": [
                {
                    "width": 458,
                    "height": 484,
                    "top": 135,
                    "left": 550
                }
            ]
        }
    },
    {
        "id": 4, 
        "boxes": {
            "0": [
                {
                    "width": 401,
                    "height": 267,
                    "top": 252,
                    "left": 15
                }
            ]
        }
    },
    {
        "id": 5,
        "boxes": {
            "0": [
                {
                    "width": 88,
                    "height": 104,
                    "top": 24,
                    "left": 256
                }
            ],
            "1": [
                {
                    "repeat_previous": true,
                    "width": 90,
                    "height": 105,
                    "top": 224,
                    "left": 257
                }
            ]
        }
    }
]